<?xml version="1.0" ?>
<!DOCTYPE main [
  <!ELEMENT main (DATA_RECORD*)>
  <!ELEMENT DATA_RECORD (APRO_LIBR_ISBN,IDPERSONA,APRO_ORDEN)+>
  <!ELEMENT APRO_LIBR_ISBN (#PCDATA)>
  <!ELEMENT IDPERSONA (#PCDATA)>
  <!ELEMENT APRO_ORDEN (#PCDATA)>
]>
<main>
  <DATA_RECORD>
    <APRO_LIBR_ISBN>978-84-313-3257-0</APRO_LIBR_ISBN>
    <IDPERSONA>16</IDPERSONA>
    <APRO_ORDEN>1</APRO_ORDEN>
  </DATA_RECORD>
  <DATA_RECORD>
    <APRO_LIBR_ISBN>978-84-9152-911-8</APRO_LIBR_ISBN>
    <IDPERSONA>59</IDPERSONA>
    <APRO_ORDEN>1</APRO_ORDEN>
  </DATA_RECORD>
  <DATA_RECORD>
    <APRO_LIBR_ISBN>978-84-16038-73-2</APRO_LIBR_ISBN>
    <IDPERSONA>2238</IDPERSONA>
    <APRO_ORDEN>2</APRO_ORDEN>
  </DATA_RECORD>
  <DATA_RECORD>
    <APRO_LIBR_ISBN>MU-686-2016</APRO_LIBR_ISBN>
    <IDPERSONA>6839</IDPERSONA>
    <APRO_ORDEN>1</APRO_ORDEN>
  </DATA_RECORD>
  <DATA_RECORD>
    <APRO_LIBR_ISBN>9788494812392</APRO_LIBR_ISBN>
    <IDPERSONA>296</IDPERSONA>
    <APRO_ORDEN>2</APRO_ORDEN>
  </DATA_RECORD>
  <DATA_RECORD>
    <APRO_LIBR_ISBN>978-84-7564-546-9</APRO_LIBR_ISBN>
    <IDPERSONA>323</IDPERSONA>
    <APRO_ORDEN>1</APRO_ORDEN>
  </DATA_RECORD>
  <DATA_RECORD>
    <APRO_LIBR_ISBN>978-84-00-09772-1</APRO_LIBR_ISBN>
    <IDPERSONA>323</IDPERSONA>
    <APRO_ORDEN>3</APRO_ORDEN>
  </DATA_RECORD>
  <DATA_RECORD>
    <APRO_LIBR_ISBN>9788494782275</APRO_LIBR_ISBN>
    <IDPERSONA>2482</IDPERSONA>
    <APRO_ORDEN>1</APRO_ORDEN>
  </DATA_RECORD>
  <DATA_RECORD>
    <APRO_LIBR_ISBN>9788494679261</APRO_LIBR_ISBN>
    <IDPERSONA>2482</IDPERSONA>
    <APRO_ORDEN>1</APRO_ORDEN>
  </DATA_RECORD>
  <DATA_RECORD>
    <APRO_LIBR_ISBN>MU-554-2017</APRO_LIBR_ISBN>
    <IDPERSONA>426</IDPERSONA>
    <APRO_ORDEN>1</APRO_ORDEN>
  </DATA_RECORD>
  <DATA_RECORD>
    <APRO_LIBR_ISBN>978-84-16165-02-5</APRO_LIBR_ISBN>
    <IDPERSONA>530</IDPERSONA>
    <APRO_ORDEN>1</APRO_ORDEN>
  </DATA_RECORD>
  <DATA_RECORD>
    <APRO_LIBR_ISBN>9788417146078</APRO_LIBR_ISBN>
    <IDPERSONA>2642</IDPERSONA>
    <APRO_ORDEN>1</APRO_ORDEN>
  </DATA_RECORD>
  <DATA_RECORD>
    <APRO_LIBR_ISBN>MU-36-2016</APRO_LIBR_ISBN>
    <IDPERSONA>2738</IDPERSONA>
    <APRO_ORDEN>1</APRO_ORDEN>
  </DATA_RECORD>
  <DATA_RECORD>
    <APRO_LIBR_ISBN>978-84-09-06300-0</APRO_LIBR_ISBN>
    <IDPERSONA>4839</IDPERSONA>
    <APRO_ORDEN>1</APRO_ORDEN>
  </DATA_RECORD>
  <DATA_RECORD>
    <APRO_LIBR_ISBN>978-84-290-1906-3</APRO_LIBR_ISBN>
    <IDPERSONA>550</IDPERSONA>
    <APRO_ORDEN>1</APRO_ORDEN>
  </DATA_RECORD>
  <DATA_RECORD>
    <APRO_LIBR_ISBN>978-84-00-09772-1</APRO_LIBR_ISBN>
    <IDPERSONA>4973</IDPERSONA>
    <APRO_ORDEN>1</APRO_ORDEN>
  </DATA_RECORD>
  <DATA_RECORD>
    <APRO_LIBR_ISBN>978-84-16724-32-1</APRO_LIBR_ISBN>
    <IDPERSONA>817</IDPERSONA>
    <APRO_ORDEN>1</APRO_ORDEN>
  </DATA_RECORD>
  <DATA_RECORD>
    <APRO_LIBR_ISBN>M-1895-2016</APRO_LIBR_ISBN>
    <IDPERSONA>2941</IDPERSONA>
    <APRO_ORDEN>1</APRO_ORDEN>
  </DATA_RECORD>
  <DATA_RECORD>
    <APRO_LIBR_ISBN>M-37905-2018</APRO_LIBR_ISBN>
    <IDPERSONA>2968</IDPERSONA>
    <APRO_ORDEN>1</APRO_ORDEN>
  </DATA_RECORD>
  <DATA_RECORD>
    <APRO_LIBR_ISBN>978-84-9744-188-9</APRO_LIBR_ISBN>
    <IDPERSONA>2968</IDPERSONA>
    <APRO_ORDEN>1</APRO_ORDEN>
  </DATA_RECORD>
  <DATA_RECORD>
    <APRO_LIBR_ISBN>978-84-376-3640-5</APRO_LIBR_ISBN>
    <IDPERSONA>2968</IDPERSONA>
    <APRO_ORDEN>1</APRO_ORDEN>
  </DATA_RECORD>
  <DATA_RECORD>
    <APRO_LIBR_ISBN>978-84-842584-4-5</APRO_LIBR_ISBN>
    <IDPERSONA>3001</IDPERSONA>
    <APRO_ORDEN>1</APRO_ORDEN>
  </DATA_RECORD>
  <DATA_RECORD>
    <APRO_LIBR_ISBN>978-84-77378-78-5</APRO_LIBR_ISBN>
    <IDPERSONA>3001</IDPERSONA>
    <APRO_ORDEN>1</APRO_ORDEN>
  </DATA_RECORD>
  <DATA_RECORD>
    <APRO_LIBR_ISBN>MU-554-2017</APRO_LIBR_ISBN>
    <IDPERSONA>7515</IDPERSONA>
    <APRO_ORDEN>2</APRO_ORDEN>
  </DATA_RECORD>
  <DATA_RECORD>
    <APRO_LIBR_ISBN>978-0-12-813054-4</APRO_LIBR_ISBN>
    <IDPERSONA>3049</IDPERSONA>
    <APRO_ORDEN>1</APRO_ORDEN>
  </DATA_RECORD>
  <DATA_RECORD>
    <APRO_LIBR_ISBN>978-84-9098-666-0</APRO_LIBR_ISBN>
    <IDPERSONA>3069</IDPERSONA>
    <APRO_ORDEN>1</APRO_ORDEN>
  </DATA_RECORD>
  <DATA_RECORD>
    <APRO_LIBR_ISBN>MU-323-2016</APRO_LIBR_ISBN>
    <IDPERSONA>3135</IDPERSONA>
    <APRO_ORDEN>1</APRO_ORDEN>
  </DATA_RECORD>
  <DATA_RECORD>
    <APRO_LIBR_ISBN>978-84-697-8356-6</APRO_LIBR_ISBN>
    <IDPERSONA>5268</IDPERSONA>
    <APRO_ORDEN>1</APRO_ORDEN>
  </DATA_RECORD>
  <DATA_RECORD>
    <APRO_LIBR_ISBN>MU 8-2017</APRO_LIBR_ISBN>
    <IDPERSONA>1020</IDPERSONA>
    <APRO_ORDEN>1</APRO_ORDEN>
  </DATA_RECORD>
  <DATA_RECORD>
    <APRO_LIBR_ISBN>MU 1139-2016</APRO_LIBR_ISBN>
    <IDPERSONA>1020</IDPERSONA>
    <APRO_ORDEN>1</APRO_ORDEN>
  </DATA_RECORD>
  <DATA_RECORD>
    <APRO_LIBR_ISBN>9788416608546</APRO_LIBR_ISBN>
    <IDPERSONA>1020</IDPERSONA>
    <APRO_ORDEN>1</APRO_ORDEN>
  </DATA_RECORD>
  <DATA_RECORD>
    <APRO_LIBR_ISBN>978-84-92602-79-7</APRO_LIBR_ISBN>
    <IDPERSONA>1020</IDPERSONA>
    <APRO_ORDEN>1</APRO_ORDEN>
  </DATA_RECORD>
  <DATA_RECORD>
    <APRO_LIBR_ISBN>978-84-16038-73-2</APRO_LIBR_ISBN>
    <IDPERSONA>1020</IDPERSONA>
    <APRO_ORDEN>1</APRO_ORDEN>
  </DATA_RECORD>
  <DATA_RECORD>
    <APRO_LIBR_ISBN>978-84-15690-83-2</APRO_LIBR_ISBN>
    <IDPERSONA>3215</IDPERSONA>
    <APRO_ORDEN>2</APRO_ORDEN>
  </DATA_RECORD>
  <DATA_RECORD>
    <APRO_LIBR_ISBN> 9788415690832</APRO_LIBR_ISBN>
    <IDPERSONA>3215</IDPERSONA>
    <APRO_ORDEN>2</APRO_ORDEN>
  </DATA_RECORD>
  <DATA_RECORD>
    <APRO_LIBR_ISBN>978-84-9985-005-4</APRO_LIBR_ISBN>
    <IDPERSONA>3226</IDPERSONA>
    <APRO_ORDEN>1</APRO_ORDEN>
  </DATA_RECORD>
  <DATA_RECORD>
    <APRO_LIBR_ISBN>978-84-9148-197-3</APRO_LIBR_ISBN>
    <IDPERSONA>3226</IDPERSONA>
    <APRO_ORDEN>1</APRO_ORDEN>
  </DATA_RECORD>
  <DATA_RECORD>
    <APRO_LIBR_ISBN>978-84-693-2246-8</APRO_LIBR_ISBN>
    <IDPERSONA>3226</IDPERSONA>
    <APRO_ORDEN>1</APRO_ORDEN>
  </DATA_RECORD>
  <DATA_RECORD>
    <APRO_LIBR_ISBN>978-84-615-8829-9</APRO_LIBR_ISBN>
    <IDPERSONA>3226</IDPERSONA>
    <APRO_ORDEN>1</APRO_ORDEN>
  </DATA_RECORD>
  <DATA_RECORD>
    <APRO_LIBR_ISBN>978-84-611-7696-0</APRO_LIBR_ISBN>
    <IDPERSONA>3226</IDPERSONA>
    <APRO_ORDEN>1</APRO_ORDEN>
  </DATA_RECORD>
  <DATA_RECORD>
    <APRO_LIBR_ISBN>978-1-78491-054-9</APRO_LIBR_ISBN>
    <IDPERSONA>3237</IDPERSONA>
    <APRO_ORDEN>1</APRO_ORDEN>
  </DATA_RECORD>
  <DATA_RECORD>
    <APRO_LIBR_ISBN>978-84-17157-24-1</APRO_LIBR_ISBN>
    <IDPERSONA>1179</IDPERSONA>
    <APRO_ORDEN>1</APRO_ORDEN>
  </DATA_RECORD>
  <DATA_RECORD>
    <APRO_LIBR_ISBN>978-84-9148-497-4</APRO_LIBR_ISBN>
    <IDPERSONA>1216</IDPERSONA>
    <APRO_ORDEN>1</APRO_ORDEN>
  </DATA_RECORD>
  <DATA_RECORD>
    <APRO_LIBR_ISBN>9788417157401</APRO_LIBR_ISBN>
    <IDPERSONA>1275</IDPERSONA>
    <APRO_ORDEN>1</APRO_ORDEN>
  </DATA_RECORD>
  <DATA_RECORD>
    <APRO_LIBR_ISBN>978-84-942014-9-3</APRO_LIBR_ISBN>
    <IDPERSONA>5709</IDPERSONA>
    <APRO_ORDEN>2</APRO_ORDEN>
  </DATA_RECORD>
  <DATA_RECORD>
    <APRO_LIBR_ISBN>978-84-16551-02-6</APRO_LIBR_ISBN>
    <IDPERSONA>1440</IDPERSONA>
    <APRO_ORDEN>1</APRO_ORDEN>
  </DATA_RECORD>
  <DATA_RECORD>
    <APRO_LIBR_ISBN>978-84-9177-726-7</APRO_LIBR_ISBN>
    <IDPERSONA>1678</IDPERSONA>
    <APRO_ORDEN>1</APRO_ORDEN>
  </DATA_RECORD>
  <DATA_RECORD>
    <APRO_LIBR_ISBN>978-84-9169-307-9</APRO_LIBR_ISBN>
    <IDPERSONA>1678</IDPERSONA>
    <APRO_ORDEN>1</APRO_ORDEN>
  </DATA_RECORD>
  <DATA_RECORD>
    <APRO_LIBR_ISBN>978-84-16608-55-3</APRO_LIBR_ISBN>
    <IDPERSONA>1678</IDPERSONA>
    <APRO_ORDEN>1</APRO_ORDEN>
  </DATA_RECORD>
  <DATA_RECORD>
    <APRO_LIBR_ISBN>978-84-16038-32-9</APRO_LIBR_ISBN>
    <IDPERSONA>1678</IDPERSONA>
    <APRO_ORDEN>1</APRO_ORDEN>
  </DATA_RECORD>
  <DATA_RECORD>
    <APRO_LIBR_ISBN>978-84-15690-83-2</APRO_LIBR_ISBN>
    <IDPERSONA>3848</IDPERSONA>
    <APRO_ORDEN>1</APRO_ORDEN>
  </DATA_RECORD>
  <DATA_RECORD>
    <APRO_LIBR_ISBN> 9788415690832</APRO_LIBR_ISBN>
    <IDPERSONA>3848</IDPERSONA>
    <APRO_ORDEN>1</APRO_ORDEN>
  </DATA_RECORD>
  <DATA_RECORD>
    <APRO_LIBR_ISBN>978-84-7564-546-9</APRO_LIBR_ISBN>
    <IDPERSONA>21502</IDPERSONA>
    <APRO_ORDEN>2</APRO_ORDEN>
  </DATA_RECORD>
  <DATA_RECORD>
    <APRO_LIBR_ISBN>551-2017</APRO_LIBR_ISBN>
    <IDPERSONA>52751</IDPERSONA>
    <APRO_ORDEN>1</APRO_ORDEN>
  </DATA_RECORD>
  <DATA_RECORD>
    <APRO_LIBR_ISBN>MU 8-2017</APRO_LIBR_ISBN>
    <IDPERSONA>115967</IDPERSONA>
    <APRO_ORDEN>2</APRO_ORDEN>
  </DATA_RECORD>
</main>
